voidgrapi/__init__.py
voidgrapi/config.py
voidgrapi/exceptions.py
voidgrapi/extractors.py
voidgrapi/image_util.py
voidgrapi/story.py
voidgrapi/types.py
voidgrapi/utils.py
voidgrapi/zones.py
voidgrapi/mixins/__init__.py
voidgrapi/mixins/account.py
voidgrapi/mixins/album.py
voidgrapi/mixins/auth.py
voidgrapi/mixins/bloks.py
voidgrapi/mixins/challenge.py
voidgrapi/mixins/clip.py
voidgrapi/mixins/collection.py
voidgrapi/mixins/comment.py
voidgrapi/mixins/direct.py
voidgrapi/mixins/explore.py
voidgrapi/mixins/fbsearch.py
voidgrapi/mixins/fundraiser.py
voidgrapi/mixins/hashtag.py
voidgrapi/mixins/highlight.py
voidgrapi/mixins/igtv.py
voidgrapi/mixins/insights.py
voidgrapi/mixins/location.py
voidgrapi/mixins/media.py
voidgrapi/mixins/multiple_accounts.py
voidgrapi/mixins/note.py
voidgrapi/mixins/notification.py
voidgrapi/mixins/password.py
voidgrapi/mixins/photo.py
voidgrapi/mixins/private.py
voidgrapi/mixins/public.py
voidgrapi/mixins/share.py
voidgrapi/mixins/signup.py
voidgrapi/mixins/story.py
voidgrapi/mixins/timeline.py
voidgrapi/mixins/totp.py
voidgrapi/mixins/track.py
voidgrapi/mixins/user.py
voidgrapi/mixins/video.py
voidgrapibro-2.1.5.post1.dist-info/licenses/LICENSE
voidgrapibro-2.1.5.post1.dist-info/METADATA
voidgrapibro-2.1.5.post1.dist-info/WHEEL
voidgrapibro-2.1.5.post1.dist-info/top_level.txt
voidgrapibro-2.1.5.post1.dist-info/RECORD
