Metadata-Version: 2.4
Name: voidgrapibro
Version: 2.1.5.post1
Summary: Custom Instagram Private API with patched behavior
Home-page: https://github.com/voiddev/voidgrapibro
Author: void
Author-email: void@users.noreply.github.com
License: MIT
Keywords: instagram,api,private api,reels,stories,uploader,custom,instagrapi,void,ratelimit bypass
Classifier: Development Status :: 4 - Beta
Classifier: Intended Audience :: Developers
Classifier: License :: OSI Approved :: MIT License
Classifier: Programming Language :: Python :: 3.9
Classifier: Programming Language :: Python :: 3.10
Requires-Python: >=3.9
License-File: LICENSE
Requires-Dist: requests<3.0,>=2.25.1
Requires-Dist: PySocks==1.7.1
Requires-Dist: pydantic==2.11.5
Requires-Dist: pycryptodomex==3.23.0
Dynamic: author
Dynamic: author-email
Dynamic: classifier
Dynamic: description
Dynamic: description-content-type
Dynamic: home-page
Dynamic: keywords
Dynamic: license
Dynamic: license-file
Dynamic: requires-dist
Dynamic: requires-python
Dynamic: summary
